<?xml version="1.0" encoding="UTF-8"?>
<objects serializationModel="Studio.02.02.00">
	<object class="AudioFile" id="{dcac6936-dc1e-4a1f-a80f-49857851604a}">
		<property name="assetPath">
			<value>Steps/Audio Track-3.wav</value>
		</property>
		<property name="frequencyInKHz">
			<value>44.0999985</value>
		</property>
		<property name="channelCount">
			<value>1</value>
		</property>
		<property name="length">
			<value>0.29791383219954648</value>
		</property>
		<relationship name="masterAssetFolder">
			<destination>{adb1a8e6-21f3-4265-b426-05904231e6b8}</destination>
		</relationship>
	</object>
</objects>
